findar/__init__.py
findar/data3.py
findar/datareader.py
findar/etf.py
findar/example2.py
findar/examples.py
findar/get_etf.py
findar/google.py
findar/quandlp.py
findar/tusharep.py
findar/utilities.py
findar-0.37.dist-info/DESCRIPTION.rst
findar-0.37.dist-info/METADATA
findar-0.37.dist-info/RECORD
findar-0.37.dist-info/WHEEL
findar-0.37.dist-info/metadata.json
findar-0.37.dist-info/top_level.txt
