Metadata-Version: 2.0
Name: findar
Version: 0.37
Summary: Financial Datareader (findar)
Home-page: https://github.com/wwengm/findar
Author: wwengm
Author-email: UNKNOWN
License: MIT
Keywords: financial data
Platform: UNKNOWN
Requires-Dist: beautifulsoup4
Requires-Dist: pandas
Requires-Dist: pandas-datareader
Requires-Dist: quandl
Requires-Dist: requests
Requires-Dist: tushare
